[{"OBJECT_NAME":"COSMOS 2433 (720)","OBJECT_ID":"2007-052A","EPOCH":"2026-03-28T04:52:50.813760","MEAN_MOTION":2.13103881,"ECCENTRICITY":0.0001116,"INCLINATION":65.6216,"RA_OF_ASC_NODE":318.6607,"ARG_OF_PERICENTER":260.7324,"MEAN_ANOMALY":99.3104,"EPHEMERIS_TYPE":0,"CLASSIFICATION_TYPE":"U","NORAD_CAT_ID":32275,"ELEMENT_SET_NO":999,"REV_AT_EPOCH":14333,"BSTAR":0,"MEAN_MOTION_DOT":-3.0e-7,"MEAN_MOTION_DDOT":0},{"OBJECT_NAME":"COSMOS 2432 (719)","OBJECT_ID":"2007-052B","EPOCH":"2026-03-27T13:39:24.382080","MEAN_MOTION":2.13103077,"ECCENTRICITY":0.0009989,"INCLINATION":65.6372,"RA_OF_ASC_NODE":318.8082,"ARG_OF_PERICENTER":334.8511,"MEAN_ANOMALY":202.7099,"EPHEMERIS_TYPE":0,"CLASSIFICATION_TYPE":"U","NORAD_CAT_ID":32276,"ELEMENT_SET_NO":999,"REV_AT_EPOCH":14334,"BSTAR":0,"MEAN_MOTION_DOT":-3.1e-7,"MEAN_MOTION_DDOT":0},{"OBJECT_NAME":"COSMOS 2434 (721)","OBJECT_ID":"2007-065A","EPOCH":"2026-03-26T11:38:23.561088","MEAN_MOTION":2.13101314,"ECCENTRICITY":0.00030088,"INCLINATION":64.3174,"RA_OF_ASC_NODE":194.7028,"ARG_OF_PERICENTER":65.629,"MEAN_ANOMALY":306.3532,"EPHEMERIS_TYPE":0,"CLASSIFICATION_TYPE":"U","NORAD_CAT_ID":32393,"ELEMENT_SET_NO":999,"REV_AT_EPOCH":14201,"BSTAR":0,"MEAN_MOTION_DOT":-1.6e-7,"MEAN_MOTION_DDOT":0},{"OBJECT_NAME":"COSMOS 2436 (723)","OBJECT_ID":"2007-065C","EPOCH":"2026-03-26T07:22:42.054816","MEAN_MOTION":2.13100149,"ECCENTRICITY":0.0017338,"INCLINATION":64.326,"RA_OF_ASC_NODE":194.7801,"ARG_OF_PERICENTER":4.3123,"MEAN_ANOMALY":4.1011,"EPHEMERIS_TYPE":0,"CLASSIFICATION_TYPE":"U","NORAD_CAT_ID":32395,"ELEMENT_SET_NO":999,"REV_AT_EPOCH":14196,"BSTAR":0,"MEAN_MOTION_DOT":-1.3e-7,"MEAN_MOTION_DDOT":0},{"OBJECT_NAME":"COSMOS 2456 (730)","OBJECT_ID":"2009-070A","EPOCH":"2026-03-27T11:08:31.240608","MEAN_MOTION":2.13103415,"ECCENTRICITY":0.0006535,"INCLINATION":64.9641,"RA_OF_ASC_NODE":73.7582,"ARG_OF_PERICENTER":309.8449,"MEAN_ANOMALY":251.0676,"EPHEMERIS_TYPE":0,"CLASSIFICATION_TYPE":"U","NORAD_CAT_ID":36111,"ELEMENT_SET_NO":999,"REV_AT_EPOCH":12668,"BSTAR":0,"MEAN_MOTION_DOT":4.1e-7,"MEAN_MOTION_DDOT":0},{"OBJECT_NAME":"COSMOS 2457 (733)","OBJECT_ID":"2009-070B","EPOCH":"2026-03-26T02:13:43.966272","MEAN_MOTION":2.13100904,"ECCENTRICITY":0.00016249,"INCLINATION":64.9488,"RA_OF_ASC_NODE":73.6506,"ARG_OF_PERICENTER":196.4354,"MEAN_ANOMALY":160.5699,"EPHEMERIS_TYPE":0,"CLASSIFICATION_TYPE":"U","NORAD_CAT_ID":36112,"ELEMENT_SET_NO":999,"REV_AT_EPOCH":12665,"BSTAR":0,"MEAN_MOTION_DOT":4.0e-7,"MEAN_MOTION_DDOT":0},{"OBJECT_NAME":"COSMOS 2460 (732)","OBJECT_ID":"2010-007C","EPOCH":"2026-03-25T09:24:39.027168","MEAN_MOTION":2.13106133,"ECCENTRICITY":0.00020622,"INCLINATION":65.4675,"RA_OF_ASC_NODE":317.3041,"ARG_OF_PERICENTER":36.6538,"MEAN_ANOMALY":143.8601,"EPHEMERIS_TYPE":0,"CLASSIFICATION_TYPE":"U","NORAD_CAT_ID":36402,"ELEMENT_SET_NO":999,"REV_AT_EPOCH":12494,"BSTAR":0,"MEAN_MOTION_DOT":-3.0e-7,"MEAN_MOTION_DDOT":0},{"OBJECT_NAME":"COSMOS 2476 (744)","OBJECT_ID":"2011-064A","EPOCH":"2026-03-22T07:44:15.606240","MEAN_MOTION":2.13103886,"ECCENTRICITY":0.00251289,"INCLINATION":65.2205,"RA_OF_ASC_NODE":75.8028,"ARG_OF_PERICENTER":241.8014,"MEAN_ANOMALY":242.7933,"EPHEMERIS_TYPE":0,"CLASSIFICATION_TYPE":"U","NORAD_CAT_ID":37867,"ELEMENT_SET_NO":999,"REV_AT_EPOCH":11191,"BSTAR":0,"MEAN_MOTION_DOT":3.4e-7,"MEAN_MOTION_DDOT":0},{"OBJECT_NAME":"COSMOS 2477 (745)","OBJECT_ID":"2011-064B","EPOCH":"2026-03-28T06:08:40.087392","MEAN_MOTION":2.13102715,"ECCENTRICITY":0.0022004,"INCLINATION":65.2312,"RA_OF_ASC_NODE":75.6808,"ARG_OF_PERICENTER":243.8544,"MEAN_ANOMALY":293.4081,"EPHEMERIS_TYPE":0,"CLASSIFICATION_TYPE":"U","NORAD_CAT_ID":37868,"ELEMENT_SET_NO":999,"REV_AT_EPOCH":11203,"BSTAR":0,"MEAN_MOTION_DOT":4.3e-7,"MEAN_MOTION_DDOT":0},{"OBJECT_NAME":"COSMOS 2475 (743)","OBJECT_ID":"2011-064C","EPOCH":"2026-03-28T18:55:41.470752","MEAN_MOTION":2.13101469,"ECCENTRICITY":0.00279516,"INCLINATION":65.2381,"RA_OF_ASC_NODE":75.6837,"ARG_OF_PERICENTER":255.2552,"MEAN_ANOMALY":286.103,"EPHEMERIS_TYPE":0,"CLASSIFICATION_TYPE":"U","NORAD_CAT_ID":37869,"ELEMENT_SET_NO":999,"REV_AT_EPOCH":11205,"BSTAR":0,"MEAN_MOTION_DOT":4.1e-7,"MEAN_MOTION_DDOT":0},{"OBJECT_NAME":"COSMOS 2485 (747)","OBJECT_ID":"2013-019A","EPOCH":"2026-03-28T04:44:19.319712","MEAN_MOTION":2.13102903,"ECCENTRICITY":0.00251415,"INCLINATION":65.375,"RA_OF_ASC_NODE":76.3211,"ARG_OF_PERICENTER":237.7712,"MEAN_ANOMALY":121.9957,"EPHEMERIS_TYPE":0,"CLASSIFICATION_TYPE":"U","NORAD_CAT_ID":39155,"ELEMENT_SET_NO":999,"REV_AT_EPOCH":10055,"BSTAR":0,"MEAN_MOTION_DOT":4.5e-7,"MEAN_MOTION_DDOT":0},{"OBJECT_NAME":"COSMOS 2492 (754)","OBJECT_ID":"2014-012A","EPOCH":"2026-03-26T06:42:14.156928","MEAN_MOTION":2.13103147,"ECCENTRICITY":0.00126427,"INCLINATION":65.3447,"RA_OF_ASC_NODE":316.7556,"ARG_OF_PERICENTER":328.9539,"MEAN_ANOMALY":31.0243,"EPHEMERIS_TYPE":0,"CLASSIFICATION_TYPE":"U","NORAD_CAT_ID":39620,"ELEMENT_SET_NO":999,"REV_AT_EPOCH":9347,"BSTAR":0,"MEAN_MOTION_DOT":-2.9e-7,"MEAN_MOTION_DDOT":0},{"OBJECT_NAME":"COSMOS 2500 (755)","OBJECT_ID":"2014-032A","EPOCH":"2026-03-28T19:06:51.677280","MEAN_MOTION":2.13105819,"ECCENTRICITY":0.00050803,"INCLINATION":65.2782,"RA_OF_ASC_NODE":316.4236,"ARG_OF_PERICENTER":190.1719,"MEAN_ANOMALY":169.8736,"EPHEMERIS_TYPE":0,"CLASSIFICATION_TYPE":"U","NORAD_CAT_ID":40001,"ELEMENT_SET_NO":999,"REV_AT_EPOCH":9174,"BSTAR":0,"MEAN_MOTION_DOT":-2.6e-7,"MEAN_MOTION_DDOT":0},{"OBJECT_NAME":"COSMOS 2501 (702K)","OBJECT_ID":"2014-075A","EPOCH":"2026-03-25T07:16:41.300256","MEAN_MOTION":2.13101287,"ECCENTRICITY":0.00211828,"INCLINATION":63.6158,"RA_OF_ASC_NODE":193.2737,"ARG_OF_PERICENTER":207.3153,"MEAN_ANOMALY":152.5805,"EPHEMERIS_TYPE":0,"CLASSIFICATION_TYPE":"U","NORAD_CAT_ID":40315,"ELEMENT_SET_NO":999,"REV_AT_EPOCH":8806,"BSTAR":0,"MEAN_MOTION_DOT":1.0e-8,"MEAN_MOTION_DDOT":0},{"OBJECT_NAME":"COSMOS 2514 (751)","OBJECT_ID":"2016-008A","EPOCH":"2026-03-28T02:28:40.623744","MEAN_MOTION":2.13102591,"ECCENTRICITY":0.0009016,"INCLINATION":65.0686,"RA_OF_ASC_NODE":315.7909,"ARG_OF_PERICENTER":203.3662,"MEAN_ANOMALY":156.6472,"EPHEMERIS_TYPE":0,"CLASSIFICATION_TYPE":"U","NORAD_CAT_ID":41330,"ELEMENT_SET_NO":999,"REV_AT_EPOCH":7889,"BSTAR":0,"MEAN_MOTION_DOT":-2.5e-7,"MEAN_MOTION_DDOT":0},{"OBJECT_NAME":"COSMOS 2522 (752)","OBJECT_ID":"2017-055A","EPOCH":"2026-03-24T04:29:20.025312","MEAN_MOTION":2.13101803,"ECCENTRICITY":0.0007868,"INCLINATION":64.0784,"RA_OF_ASC_NODE":194.7748,"ARG_OF_PERICENTER":230.2375,"MEAN_ANOMALY":129.7005,"EPHEMERIS_TYPE":0,"CLASSIFICATION_TYPE":"U","NORAD_CAT_ID":42939,"ELEMENT_SET_NO":999,"REV_AT_EPOCH":6616,"BSTAR":0,"MEAN_MOTION_DOT":2.0e-7,"MEAN_MOTION_DDOT":0},{"OBJECT_NAME":"COSMOS 2527 (756)","OBJECT_ID":"2018-053A","EPOCH":"2026-03-28T08:55:12.126432","MEAN_MOTION":2.1310196,"ECCENTRICITY":0.00093087,"INCLINATION":65.5335,"RA_OF_ASC_NODE":76.6017,"ARG_OF_PERICENTER":247.7954,"MEAN_ANOMALY":112.1166,"EPHEMERIS_TYPE":0,"CLASSIFICATION_TYPE":"U","NORAD_CAT_ID":43508,"ELEMENT_SET_NO":999,"REV_AT_EPOCH":6055,"BSTAR":0,"MEAN_MOTION_DOT":4.6e-7,"MEAN_MOTION_DDOT":0},{"OBJECT_NAME":"COSMOS 2529 (757)","OBJECT_ID":"2018-086A","EPOCH":"2026-03-25T04:24:38.012256","MEAN_MOTION":2.13101936,"ECCENTRICITY":0.00087146,"INCLINATION":64.2947,"RA_OF_ASC_NODE":195.4281,"ARG_OF_PERICENTER":253.5032,"MEAN_ANOMALY":106.4055,"EPHEMERIS_TYPE":0,"CLASSIFICATION_TYPE":"U","NORAD_CAT_ID":43687,"ELEMENT_SET_NO":999,"REV_AT_EPOCH":5749,"BSTAR":0,"MEAN_MOTION_DOT":5.0e-8,"MEAN_MOTION_DDOT":0},{"OBJECT_NAME":"COSMOS 2534 (758)","OBJECT_ID":"2019-030A","EPOCH":"2026-03-26T22:51:06.084864","MEAN_MOTION":2.13102185,"ECCENTRICITY":0.0010587,"INCLINATION":64.3675,"RA_OF_ASC_NODE":195.3834,"ARG_OF_PERICENTER":278.5139,"MEAN_ANOMALY":132.529,"EPHEMERIS_TYPE":0,"CLASSIFICATION_TYPE":"U","NORAD_CAT_ID":44299,"ELEMENT_SET_NO":999,"REV_AT_EPOCH":5317,"BSTAR":0,"MEAN_MOTION_DOT":-2.2e-7,"MEAN_MOTION_DDOT":0},{"OBJECT_NAME":"COSMOS 2544 (759)","OBJECT_ID":"2019-088A","EPOCH":"2026-03-23T14:58:07.497696","MEAN_MOTION":2.1310202,"ECCENTRICITY":0.00157911,"INCLINATION":65.5174,"RA_OF_ASC_NODE":76.5851,"ARG_OF_PERICENTER":260.6166,"MEAN_ANOMALY":99.2133,"EPHEMERIS_TYPE":0,"CLASSIFICATION_TYPE":"U","NORAD_CAT_ID":44850,"ELEMENT_SET_NO":999,"REV_AT_EPOCH":4889,"BSTAR":0,"MEAN_MOTION_DOT":3.6e-7,"MEAN_MOTION_DDOT":0},{"OBJECT_NAME":"COSMOS 2545 (760)","OBJECT_ID":"2020-018A","EPOCH":"2026-03-26T03:58:22.686240","MEAN_MOTION":2.13102438,"ECCENTRICITY":0.00074746,"INCLINATION":64.4042,"RA_OF_ASC_NODE":315.3386,"ARG_OF_PERICENTER":246.9709,"MEAN_ANOMALY":113.0018,"EPHEMERIS_TYPE":0,"CLASSIFICATION_TYPE":"U","NORAD_CAT_ID":45358,"ELEMENT_SET_NO":999,"REV_AT_EPOCH":4689,"BSTAR":0,"MEAN_MOTION_DOT":-2.8e-7,"MEAN_MOTION_DDOT":0},{"OBJECT_NAME":"COSMOS 2547 (705K)","OBJECT_ID":"2020-075A","EPOCH":"2026-03-27T18:17:20.941152","MEAN_MOTION":2.13100219,"ECCENTRICITY":0.00073709,"INCLINATION":64.5985,"RA_OF_ASC_NODE":195.1905,"ARG_OF_PERICENTER":232.5213,"MEAN_ANOMALY":127.4084,"EPHEMERIS_TYPE":0,"CLASSIFICATION_TYPE":"U","NORAD_CAT_ID":46805,"ELEMENT_SET_NO":999,"REV_AT_EPOCH":4217,"BSTAR":0,"MEAN_MOTION_DOT":-3.1e-7,"MEAN_MOTION_DDOT":0},{"OBJECT_NAME":"COSMOS 2557 (706K)","OBJECT_ID":"2022-075A","EPOCH":"2026-03-28T09:30:36.463104","MEAN_MOTION":2.13101758,"ECCENTRICITY":0.0010963,"INCLINATION":64.3446,"RA_OF_ASC_NODE":317.3335,"ARG_OF_PERICENTER":283.619,"MEAN_ANOMALY":76.3135,"EPHEMERIS_TYPE":0,"CLASSIFICATION_TYPE":"U","NORAD_CAT_ID":52984,"ELEMENT_SET_NO":999,"REV_AT_EPOCH":2899,"BSTAR":0,"MEAN_MOTION_DOT":-3.1e-7,"MEAN_MOTION_DDOT":0},{"OBJECT_NAME":"COSMOS 2559 (707K)","OBJECT_ID":"2022-130A","EPOCH":"2026-03-27T06:39:07.070688","MEAN_MOTION":2.13101261,"ECCENTRICITY":0.0010826,"INCLINATION":64.318,"RA_OF_ASC_NODE":317.4582,"ARG_OF_PERICENTER":178.2697,"MEAN_ANOMALY":181.7868,"EPHEMERIS_TYPE":0,"CLASSIFICATION_TYPE":"U","NORAD_CAT_ID":54031,"ELEMENT_SET_NO":999,"REV_AT_EPOCH":2694,"BSTAR":0,"MEAN_MOTION_DOT":-3.1e-7,"MEAN_MOTION_DDOT":0},{"OBJECT_NAME":"COSMOS 2564 (761)","OBJECT_ID":"2022-161A","EPOCH":"2026-03-28T12:40:52.220352","MEAN_MOTION":2.13101826,"ECCENTRICITY":0.00101426,"INCLINATION":64.7402,"RA_OF_ASC_NODE":195.3871,"ARG_OF_PERICENTER":214.6858,"MEAN_ANOMALY":145.2434,"EPHEMERIS_TYPE":0,"CLASSIFICATION_TYPE":"U","NORAD_CAT_ID":54377,"ELEMENT_SET_NO":999,"REV_AT_EPOCH":2591,"BSTAR":0,"MEAN_MOTION_DOT":-3.5e-7,"MEAN_MOTION_DDOT":0},{"OBJECT_NAME":"COSMOS 2569 (703K)","OBJECT_ID":"2023-114A","EPOCH":"2026-03-28T12:59:13.416000","MEAN_MOTION":2.13103807,"ECCENTRICITY":0.00129072,"INCLINATION":65.2574,"RA_OF_ASC_NODE":75.3385,"ARG_OF_PERICENTER":293.4527,"MEAN_ANOMALY":66.4203,"EPHEMERIS_TYPE":0,"CLASSIFICATION_TYPE":"U","NORAD_CAT_ID":57517,"ELEMENT_SET_NO":999,"REV_AT_EPOCH":2054,"BSTAR":0,"MEAN_MOTION_DOT":4.1e-7,"MEAN_MOTION_DDOT":0},{"OBJECT_NAME":"COSMOS 2584 (704K)","OBJECT_ID":"2025-042A","EPOCH":"2026-03-27T23:00:36.984096","MEAN_MOTION":2.13103439,"ECCENTRICITY":0.00074322,"INCLINATION":65.039,"RA_OF_ASC_NODE":75.5619,"ARG_OF_PERICENTER":238.763,"MEAN_ANOMALY":121.1744,"EPHEMERIS_TYPE":0,"CLASSIFICATION_TYPE":"U","NORAD_CAT_ID":63130,"ELEMENT_SET_NO":999,"REV_AT_EPOCH":831,"BSTAR":0,"MEAN_MOTION_DOT":4.4e-7,"MEAN_MOTION_DDOT":0},{"OBJECT_NAME":"COSMOS 2596 (708K)","OBJECT_ID":"2025-206B","EPOCH":"2026-03-27T14:45:45.838368","MEAN_MOTION":2.13100192,"ECCENTRICITY":0.0012287,"INCLINATION":64.6808,"RA_OF_ASC_NODE":317.8263,"ARG_OF_PERICENTER":316.8794,"MEAN_ANOMALY":256.7022,"EPHEMERIS_TYPE":0,"CLASSIFICATION_TYPE":"U","NORAD_CAT_ID":65590,"ELEMENT_SET_NO":999,"REV_AT_EPOCH":417,"BSTAR":0,"MEAN_MOTION_DOT":-3.1e-7,"MEAN_MOTION_DDOT":0}]
